nose_sfd-0.4.dist-info/metadata.json
nose_sfd-0.4.dist-info/METADATA
nose_sfd-0.4.dist-info/entry_points.txt
nose_sfd-0.4.dist-info/RECORD
nose_sfd-0.4.dist-info/WHEEL
nose_sfd-0.4.dist-info/DESCRIPTION.rst
nose_sfd-0.4.dist-info/top_level.txt
sfd/sfd.py
sfd/__init__.py
