Metadata-Version: 2.0
Name: nose-sfd
Version: 0.4
Summary: nose plugin for testing Django projects in a faster way.
Home-page: https://github.com/Fantomas42/nose-sfd
Author: Fantomas42
Author-email: fantomas42@gmail.com
License: GNU LGPL
Keywords: nose,django,tests
Platform: UNKNOWN
Classifier: Framework :: Django
Classifier: Development Status :: 5 - Production/Stable
Classifier: Programming Language :: Python
Classifier: Intended Audience :: Developers
Classifier: Operating System :: OS Independent
Classifier: Topic :: Software Development :: Testing
Classifier: License :: OSI Approved :: GNU Library or Lesser General Public License (LGPL)
Requires-Dist: nose (>=0.10)
